<?xml version="1.0" encoding="UTF-8"?>
<list xmlns:xsi="http://www.w3.org/2001/XMLSchema-instance" xsi:noNamespaceSchemaLocation="../../xsd/spawns.xsd">
	<spawn name="MailleLizardmenBarracks">
		<group>
			<npc id="20923" x="-22490" y="101358" z="-3656" heading="20125" respawnTime="60sec" /> <!-- Maille Lizardman Shaman -->
			<npc id="20923" x="-22809" y="100571" z="-3632" heading="23278" respawnTime="60sec" /> <!-- Maille Lizardman Shaman -->
			<npc id="20923" x="-22957" y="100826" z="-3648" heading="61345" respawnTime="60sec" /> <!-- Maille Lizardman Shaman -->
			<npc id="20923" x="-23717" y="102400" z="-3656" heading="23708" respawnTime="60sec" /> <!-- Maille Lizardman Shaman -->
			<npc id="20923" x="-23774" y="102604" z="-3648" heading="8870" respawnTime="60sec" /> <!-- Maille Lizardman Shaman -->
			<npc id="20923" x="-23924" y="103511" z="-3568" heading="59002" respawnTime="60sec" /> <!-- Maille Lizardman Shaman -->
			<npc id="20923" x="-24199" y="104269" z="-3512" heading="58800" respawnTime="60sec" /> <!-- Maille Lizardman Shaman -->
			<npc id="20923" x="-24569" y="105732" z="-3528" heading="19855" respawnTime="60sec" /> <!-- Maille Lizardman Shaman -->
			<npc id="20923" x="-24944" y="102112" z="-3624" heading="56583" respawnTime="60sec" /> <!-- Maille Lizardman Shaman -->
			<npc id="20923" x="-25223" y="103208" z="-3384" heading="28368" respawnTime="60sec" /> <!-- Maille Lizardman Shaman -->
			<npc id="20923" x="-25449" y="102795" z="-3384" heading="36330" respawnTime="60sec" /> <!-- Maille Lizardman Shaman -->
			<npc id="20923" x="-25473" y="104347" z="-3400" heading="57430" respawnTime="60sec" /> <!-- Maille Lizardman Shaman -->
			<npc id="20923" x="-25796" y="102365" z="-3520" heading="50480" respawnTime="60sec" /> <!-- Maille Lizardman Shaman -->
			<npc id="20923" x="-27209" y="106550" z="-3720" heading="45644" respawnTime="60sec" /> <!-- Maille Lizardman Shaman -->
			<npc id="20923" x="-27822" y="104865" z="-3712" heading="58536" respawnTime="60sec" /> <!-- Maille Lizardman Shaman -->
			<npc id="20923" x="-27982" y="100386" z="-3720" heading="39578" respawnTime="60sec" /> <!-- Maille Lizardman Shaman -->
			<npc id="20923" x="-28193" y="106269" z="-3584" heading="10351" respawnTime="60sec" /> <!-- Maille Lizardman Shaman -->
			<npc id="20923" x="-28422" y="105528" z="-3584" heading="62219" respawnTime="60sec" /> <!-- Maille Lizardman Shaman -->
			<npc id="20923" x="-28486" y="101293" z="-3640" heading="59806" respawnTime="60sec" /> <!-- Maille Lizardman Shaman -->
			<npc id="20923" x="-28529" y="109654" z="-3704" heading="31976" respawnTime="60sec" /> <!-- Maille Lizardman Shaman -->
			<npc id="20923" x="-28766" y="108832" z="-3696" heading="61747" respawnTime="60sec" /> <!-- Maille Lizardman Shaman -->
			<npc id="20923" x="-28991" y="104321" z="-3576" heading="2819" respawnTime="60sec" /> <!-- Maille Lizardman Shaman -->
			<npc id="20923" x="-29165" y="105022" z="-3512" heading="1087" respawnTime="60sec" /> <!-- Maille Lizardman Shaman -->
			<npc id="20923" x="-29234" y="102918" z="-3592" heading="5775" respawnTime="60sec" /> <!-- Maille Lizardman Shaman -->
			<npc id="20923" x="-29236" y="106469" z="-3520" heading="0" respawnTime="60sec" /> <!-- Maille Lizardman Shaman -->
			<npc id="20923" x="-29261" y="103543" z="-3600" heading="33137" respawnTime="60sec" /> <!-- Maille Lizardman Shaman -->
			<npc id="20923" x="-29509" y="104811" z="-3472" heading="18761" respawnTime="60sec" /> <!-- Maille Lizardman Shaman -->
			<npc id="20923" x="-29737" y="102094" z="-3528" heading="6582" respawnTime="60sec" /> <!-- Maille Lizardman Shaman -->
			<npc id="20923" x="-29873" y="100947" z="-3536" heading="21728" respawnTime="60sec" /> <!-- Maille Lizardman Shaman -->
			<npc id="20923" x="-30501" y="101184" z="-3496" heading="7761" respawnTime="60sec" /> <!-- Maille Lizardman Shaman -->
			<npc id="20923" x="-30592" y="101938" z="-3368" heading="39845" respawnTime="60sec" /> <!-- Maille Lizardman Shaman -->
			<npc id="20923" x="-30674" y="103758" z="-3256" heading="47331" respawnTime="60sec" /> <!-- Maille Lizardman Shaman -->
			<npc id="20923" x="-30967" y="99304" z="-3704" heading="41246" respawnTime="60sec" /> <!-- Maille Lizardman Shaman -->
			<npc id="20923" x="-31028" y="105285" z="-3088" heading="54851" respawnTime="60sec" /> <!-- Maille Lizardman Shaman -->
			<npc id="20923" x="-31073" y="99488" z="-3672" heading="20671" respawnTime="60sec" /> <!-- Maille Lizardman Shaman -->
			<npc id="20923" x="-31147" y="99438" z="-3704" heading="49879" respawnTime="60sec" /> <!-- Maille Lizardman Shaman -->
			<npc id="20923" x="-31252" y="107082" z="-3264" heading="1586" respawnTime="60sec" /> <!-- Maille Lizardman Shaman -->
			<npc id="20923" x="-31410" y="100430" z="-3592" heading="60162" respawnTime="60sec" /> <!-- Maille Lizardman Shaman -->
			<npc id="20923" x="-31782" y="103752" z="-2960" heading="40403" respawnTime="60sec" /> <!-- Maille Lizardman Shaman -->
			<npc id="20923" x="-31813" y="107727" z="-3216" heading="23713" respawnTime="60sec" /> <!-- Maille Lizardman Shaman -->
			<npc id="20923" x="-31866" y="107814" z="-3184" heading="46598" respawnTime="60sec" /> <!-- Maille Lizardman Shaman -->
			<npc id="20923" x="-32076" y="105351" z="-2912" heading="484" respawnTime="60sec" /> <!-- Maille Lizardman Shaman -->
			<npc id="20923" x="-32350" y="104809" z="-2776" heading="52942" respawnTime="60sec" /> <!-- Maille Lizardman Shaman -->
			<npc id="20923" x="-32447" y="104960" z="-2744" heading="43391" respawnTime="60sec" /> <!-- Maille Lizardman Shaman -->
			<npc id="20924" x="-23107" y="100147" z="-3592" heading="47349" respawnTime="60sec" /> <!-- Maille Lizardman Matriarch -->
			<npc id="20924" x="-23177" y="99574" z="-3640" heading="63855" respawnTime="60sec" /> <!-- Maille Lizardman Matriarch -->
			<npc id="20924" x="-23813" y="102484" z="-3648" heading="11215" respawnTime="60sec" /> <!-- Maille Lizardman Matriarch -->
			<npc id="20924" x="-23852" y="101961" z="-3688" heading="14745" respawnTime="60sec" /> <!-- Maille Lizardman Matriarch -->
			<npc id="20924" x="-23865" y="100726" z="-3688" heading="7730" respawnTime="60sec" /> <!-- Maille Lizardman Matriarch -->
			<npc id="20924" x="-23992" y="102429" z="-3632" heading="10587" respawnTime="60sec" /> <!-- Maille Lizardman Matriarch -->
			<npc id="20924" x="-25077" y="102302" z="-3576" heading="6339" respawnTime="60sec" /> <!-- Maille Lizardman Matriarch -->
			<npc id="20924" x="-25183" y="104363" z="-3432" heading="2104" respawnTime="60sec" /> <!-- Maille Lizardman Matriarch -->
			<npc id="20924" x="-25645" y="101492" z="-3704" heading="61476" respawnTime="60sec" /> <!-- Maille Lizardman Matriarch -->
			<npc id="20924" x="-26222" y="104151" z="-3312" heading="26980" respawnTime="60sec" /> <!-- Maille Lizardman Matriarch -->
			<npc id="20924" x="-26316" y="103737" z="-3280" heading="40214" respawnTime="60sec" /> <!-- Maille Lizardman Matriarch -->
			<npc id="20924" x="-26360" y="104074" z="-3280" heading="18461" respawnTime="60sec" /> <!-- Maille Lizardman Matriarch -->
			<npc id="20924" x="-27172" y="105727" z="-3720" heading="51212" respawnTime="60sec" /> <!-- Maille Lizardman Matriarch -->
			<npc id="20924" x="-27447" y="106584" z="-3720" heading="39487" respawnTime="60sec" /> <!-- Maille Lizardman Matriarch -->
			<npc id="20924" x="-27793" y="100629" z="-3720" heading="18451" respawnTime="60sec" /> <!-- Maille Lizardman Matriarch -->
			<npc id="20924" x="-28039" y="100495" z="-3720" heading="21806" respawnTime="60sec" /> <!-- Maille Lizardman Matriarch -->
			<npc id="20924" x="-28441" y="100802" z="-3672" heading="46357" respawnTime="60sec" /> <!-- Maille Lizardman Matriarch -->
			<npc id="20924" x="-28685" y="106684" z="-3568" heading="17441" respawnTime="60sec" /> <!-- Maille Lizardman Matriarch -->
			<npc id="20924" x="-29161" y="109200" z="-3688" heading="15820" respawnTime="60sec" /> <!-- Maille Lizardman Matriarch -->
			<npc id="20924" x="-29333" y="105536" z="-3448" heading="36303" respawnTime="60sec" /> <!-- Maille Lizardman Matriarch -->
			<npc id="20924" x="-29336" y="99793" z="-3656" heading="43984" respawnTime="60sec" /> <!-- Maille Lizardman Matriarch -->
			<npc id="20924" x="-29388" y="104921" z="-3496" heading="3502" respawnTime="60sec" /> <!-- Maille Lizardman Matriarch -->
			<npc id="20924" x="-29405" y="104887" z="-3496" heading="1539" respawnTime="60sec" /> <!-- Maille Lizardman Matriarch -->
			<npc id="20924" x="-29542" y="101413" z="-3560" heading="60122" respawnTime="60sec" /> <!-- Maille Lizardman Matriarch -->
			<npc id="20924" x="-29737" y="100835" z="-3552" heading="36853" respawnTime="60sec" /> <!-- Maille Lizardman Matriarch -->
			<npc id="20924" x="-29933" y="106144" z="-3400" heading="15446" respawnTime="60sec" /> <!-- Maille Lizardman Matriarch -->
			<npc id="20924" x="-29980" y="104284" z="-3176" heading="59549" respawnTime="60sec" /> <!-- Maille Lizardman Matriarch -->
			<npc id="20924" x="-30184" y="103117" z="-3416" heading="52246" respawnTime="60sec" /> <!-- Maille Lizardman Matriarch -->
			<npc id="20924" x="-30366" y="101303" z="-3488" heading="4965" respawnTime="60sec" /> <!-- Maille Lizardman Matriarch -->
			<npc id="20924" x="-30445" y="104117" z="-3288" heading="26477" respawnTime="60sec" /> <!-- Maille Lizardman Matriarch -->
			<npc id="20924" x="-30530" y="104072" z="-3248" heading="39314" respawnTime="60sec" /> <!-- Maille Lizardman Matriarch -->
			<npc id="20924" x="-30951" y="102517" z="-3288" heading="49525" respawnTime="60sec" /> <!-- Maille Lizardman Matriarch -->
			<npc id="20924" x="-31085" y="104783" z="-3120" heading="42813" respawnTime="60sec" /> <!-- Maille Lizardman Matriarch -->
			<npc id="20924" x="-31360" y="103970" z="-3096" heading="43149" respawnTime="60sec" /> <!-- Maille Lizardman Matriarch -->
			<npc id="20924" x="-31597" y="107314" z="-3272" heading="48533" respawnTime="60sec" /> <!-- Maille Lizardman Matriarch -->
			<npc id="20924" x="-31709" y="107675" z="-3272" heading="60306" respawnTime="60sec" /> <!-- Maille Lizardman Matriarch -->
			<npc id="20924" x="-32075" y="101463" z="-3368" heading="7863" respawnTime="60sec" /> <!-- Maille Lizardman Matriarch -->
			<npc id="20924" x="-32138" y="107338" z="-3032" heading="10922" respawnTime="60sec" /> <!-- Maille Lizardman Matriarch -->
			<npc id="20924" x="-32329" y="107443" z="-2888" heading="55862" respawnTime="60sec" /> <!-- Maille Lizardman Matriarch -->
			<npc id="20924" x="-32343" y="104000" z="-2800" heading="45650" respawnTime="60sec" /> <!-- Maille Lizardman Matriarch -->
			<npc id="20924" x="-32585" y="99486" z="-3720" heading="34584" respawnTime="60sec" /> <!-- Maille Lizardman Matriarch -->
		</group>
	</spawn>
</list>
